curveball/__init__.py
curveball/_version.py
curveball/baranyi_roberts_model.py
curveball/competitions.py
curveball/ioutils.py
curveball/likelihood.py
curveball/models.py
curveball/plots.py
curveball/utils.py
curveball/scripts/__init__.py
curveball/scripts/cli.py
curveball-0.3.0.data/data/data/20130211_dh.zip
curveball-0.3.0.data/data/data/BioTekSynergy.xlsx
curveball-0.3.0.data/data/data/Sunrise_180515_0916.xlsx
curveball-0.3.0.data/data/data/Tecan_210115.csv
curveball-0.3.0.data/data/data/Tecan_210115.xlsx
curveball-0.3.0.data/data/data/Tecan_280715.xlsx
curveball-0.3.0.data/data/data/plate_9_OD.mat
curveball-0.3.0.data/data/plate_templates/G-RG-R.csv
curveball-0.3.0.data/data/plate_templates/checkerboard.csv
curveball-0.3.0.dist-info/licenses/LICENCE.txt
data/20130211_dh.zip
data/BioTekSynergy.xlsx
data/Spectramax_growth_curve.txt
data/Sunrise_180515_0916.xlsx
data/Tecan_210115.csv
data/Tecan_210115.xlsx
data/Tecan_280715.xlsx
data/Tecan_280715_RG_vs_G.png
data/Tecan_280715_R_vs_G.png
data/Tecan_280715_strain_G.png
data/Tecan_280715_strain_R.png
data/Tecan_280715_strain_RG.png
data/Tecan_280715_strains.png
data/Tecan_280715_wells.png
data/__init__.py
data/plate_9_OD.mat
plate_templates/DH5a-TG1.csv
plate_templates/DH5a-s12-TG1.csv
plate_templates/G-RG-R.csv
plate_templates/__init__.py
plate_templates/checkerboard.csv
plate_templates/checkerboard2.csv
plate_templates/nine-strains.csv
plate_templates/six-strains.csv
tests/__init__.py
tests/base.py
tests/test_cli.py
tests/test_competitions.py
tests/test_ioutils.py
tests/test_likelihood.py
tests/test_models.py
tests/test_plots.py
curveball-0.3.0.dist-info/METADATA
curveball-0.3.0.dist-info/WHEEL
curveball-0.3.0.dist-info/entry_points.txt
curveball-0.3.0.dist-info/top_level.txt
curveball-0.3.0.dist-info/RECORD
