Metadata-Version: 2.4
Name: curveball
Version: 0.3.0
Summary: Predicting competition results from growth curves
Home-page: https://github.com/yoavram/curveball
Author: Yoav Ram
Author-email: yoav@yoavram.com
License: MIT
Keywords: microbiology biomath evolution
Classifier: Development Status :: 3 - Alpha
Classifier: Intended Audience :: Developers
Classifier: Intended Audience :: End Users/Desktop
Classifier: Intended Audience :: Science/Research
Classifier: Topic :: Scientific/Engineering :: Bio-Informatics
Classifier: License :: OSI Approved :: MIT License
Classifier: Natural Language :: English
Classifier: Programming Language :: Python :: 3.6
Classifier: Programming Language :: Python :: 3.7
Classifier: Programming Language :: Python :: 3.8
Classifier: Programming Language :: Python :: 3.9
Classifier: Operating System :: OS Independent
License-File: LICENCE.txt
Requires-Dist: future>=0.18.0
Requires-Dist: click>=7.0
Requires-Dist: lxml>=4.7.0
Requires-Dist: xlrd<2.0,>=1.2.0
Requires-Dist: numpy>=1.20.0
Requires-Dist: scipy>=1.6.0
Requires-Dist: matplotlib>=3.2.0
Requires-Dist: pandas>=1.3.0
Requires-Dist: seaborn>=0.11.0
Requires-Dist: scikit-learn>=0.24.0
Requires-Dist: sympy>=1.9.0
Requires-Dist: lmfit>=1.0.0
Requires-Dist: webcolors>=1.7
Requires-Dist: python-dateutil>=2.8.0
Provides-Extra: tests
Requires-Dist: pytest; extra == "tests"
Requires-Dist: pytest-cov; extra == "tests"
Requires-Dist: pillow; extra == "tests"
Provides-Extra: docs
Requires-Dist: sphinx>=1.3.0; extra == "docs"
Requires-Dist: numpydoc; extra == "docs"
Requires-Dist: sphinx_rtd_theme; extra == "docs"
Dynamic: author
Dynamic: author-email
Dynamic: classifier
Dynamic: description
Dynamic: description-content-type
Dynamic: home-page
Dynamic: keywords
Dynamic: license
Dynamic: license-file
Dynamic: provides-extra
Dynamic: requires-dist
Dynamic: summary
